MANIFEST.in
README.md
setup.py
./CMakeLists.txt
./dltpy/native/CMakeLists.txt
./dltpy/native/bitmasks.h
./dltpy/native/dltreader.cpp
./dltpy/native/dltreader.h
./dltpy/native/dltreader_native.cpp
./dltpy/native/headers.h
./dltpy/native/log.cpp
./dltpy/native/log.h
./dltpy/native/parsers.h
./dltpy/native/pybind11/CMakeLists.txt
./dltpy/native/pybind11/include/pybind11/attr.h
./dltpy/native/pybind11/include/pybind11/buffer_info.h
./dltpy/native/pybind11/include/pybind11/cast.h
./dltpy/native/pybind11/include/pybind11/chrono.h
./dltpy/native/pybind11/include/pybind11/common.h
./dltpy/native/pybind11/include/pybind11/complex.h
./dltpy/native/pybind11/include/pybind11/eigen.h
./dltpy/native/pybind11/include/pybind11/embed.h
./dltpy/native/pybind11/include/pybind11/eval.h
./dltpy/native/pybind11/include/pybind11/functional.h
./dltpy/native/pybind11/include/pybind11/iostream.h
./dltpy/native/pybind11/include/pybind11/numpy.h
./dltpy/native/pybind11/include/pybind11/operators.h
./dltpy/native/pybind11/include/pybind11/options.h
./dltpy/native/pybind11/include/pybind11/pybind11.h
./dltpy/native/pybind11/include/pybind11/pytypes.h
./dltpy/native/pybind11/include/pybind11/stl.h
./dltpy/native/pybind11/include/pybind11/stl_bind.h
./dltpy/native/pybind11/include/pybind11/detail/class.h
./dltpy/native/pybind11/include/pybind11/detail/common.h
./dltpy/native/pybind11/include/pybind11/detail/descr.h
./dltpy/native/pybind11/include/pybind11/detail/init.h
./dltpy/native/pybind11/include/pybind11/detail/internals.h
./dltpy/native/pybind11/include/pybind11/detail/typeid.h
./dltpy/native/pybind11/tests/CMakeLists.txt
./dltpy/native/pybind11/tests/constructor_stats.h
./dltpy/native/pybind11/tests/cross_module_gil_utils.cpp
./dltpy/native/pybind11/tests/local_bindings.h
./dltpy/native/pybind11/tests/object.h
./dltpy/native/pybind11/tests/pybind11_cross_module_tests.cpp
./dltpy/native/pybind11/tests/pybind11_tests.cpp
./dltpy/native/pybind11/tests/pybind11_tests.h
dltpy.egg-info/PKG-INFO
dltpy.egg-info/SOURCES.txt
dltpy.egg-info/dependency_links.txt
dltpy.egg-info/entry_points.txt
dltpy.egg-info/requires.txt
dltpy.egg-info/top_level.txt
