Metadata-Version: 2.1
Name: dltpy
Version: 0.3.6.9
Summary: DLT log reader
Home-page: https://github.com/Equidamoid/dltpy
Author: Vladimir Shapranov
Author-email: equidamoid@gmail.com
License: UNKNOWN
Platform: UNKNOWN
Classifier: License :: OSI Approved :: GNU General Public License v3 (GPLv3)
Classifier: Development Status :: 3 - Alpha
Classifier: Intended Audience :: Developers
Classifier: Operating System :: POSIX :: Linux
Classifier: Operating System :: MacOS :: MacOS X
Classifier: Programming Language :: Python :: 3.5
Classifier: Programming Language :: Python :: 3.6
Classifier: Programming Language :: Python :: 3.7
